{"errors":[],"warnings":["chunk styles [mini-css-extract-plugin]\nConflicting order between:\n * css ./node_modules/css-loader??ref--10-oneOf-1-1!./node_modules/postcss-loader/lib??postcss-2!./node_modules/gatsby-plugin-transition-link/style.css\n * css ./node_modules/css-loader??ref--10-oneOf-1-1!./node_modules/postcss-loader/lib??postcss-2!./node_modules/typeface-eb-garamond/index.css","chunk styles [mini-css-extract-plugin]\nConflicting order between:\n * css ./node_modules/css-loader??ref--10-oneOf-1-1!./node_modules/postcss-loader/lib??postcss-2!./node_modules/prismjs/themes/prism.css\n * css ./node_modules/css-loader??ref--10-oneOf-1-1!./node_modules/postcss-loader/lib??postcss-2!./node_modules/typeface-eb-garamond/index.css"],"namedChunkGroups":{"app":{"chunks":[11,0,3],"assets":["webpack-runtime-3320b42780cefc6625f2.js","webpack-runtime-3320b42780cefc6625f2.js.map","styles.b6947980c7644db60460.css","styles-be8105c56c1a09dbbca6.js","styles-be8105c56c1a09dbbca6.js.map","app-a7fe1f09c92da344b0fd.js","app-a7fe1f09c92da344b0fd.js.map"],"children":{},"childAssets":{}},"component---src-templates-case-study-jsx":{"chunks":[0,1,2,9],"assets":["styles.b6947980c7644db60460.css","styles-be8105c56c1a09dbbca6.js","styles-be8105c56c1a09dbbca6.js.map","1-2d947e67ed2878270b86.js","1-2d947e67ed2878270b86.js.map","2-ee542a1a022b7a037d70.js","2-ee542a1a022b7a037d70.js.map","component---src-templates-case-study-jsx-dedb2418065911020a35.js","component---src-templates-case-study-jsx-dedb2418065911020a35.js.map"],"children":{},"childAssets":{}},"component---src-templates-blog-jsx":{"chunks":[0,1,12,2,8],"assets":["styles.b6947980c7644db60460.css","styles-be8105c56c1a09dbbca6.js","styles-be8105c56c1a09dbbca6.js.map","1-2d947e67ed2878270b86.js","1-2d947e67ed2878270b86.js.map","12-e8ccbfaec0dc63ed60c8.js","12-e8ccbfaec0dc63ed60c8.js.map","2-ee542a1a022b7a037d70.js","2-ee542a1a022b7a037d70.js.map","component---src-templates-blog-jsx-bde74e2a60b696371382.js","component---src-templates-blog-jsx-bde74e2a60b696371382.js.map"],"children":{},"childAssets":{}},"component---src-pages-404-jsx":{"chunks":[0,1,2,4],"assets":["styles.b6947980c7644db60460.css","styles-be8105c56c1a09dbbca6.js","styles-be8105c56c1a09dbbca6.js.map","1-2d947e67ed2878270b86.js","1-2d947e67ed2878270b86.js.map","2-ee542a1a022b7a037d70.js","2-ee542a1a022b7a037d70.js.map","component---src-pages-404-jsx-b407729bf74e3ba0101e.js","component---src-pages-404-jsx-b407729bf74e3ba0101e.js.map"],"children":{},"childAssets":{}},"component---src-pages-blog-jsx":{"chunks":[0,1,2,5],"assets":["styles.b6947980c7644db60460.css","styles-be8105c56c1a09dbbca6.js","styles-be8105c56c1a09dbbca6.js.map","1-2d947e67ed2878270b86.js","1-2d947e67ed2878270b86.js.map","2-ee542a1a022b7a037d70.js","2-ee542a1a022b7a037d70.js.map","component---src-pages-blog-jsx-b59c7f80df31187fe70d.js","component---src-pages-blog-jsx-b59c7f80df31187fe70d.js.map"],"children":{},"childAssets":{}},"component---src-pages-index-jsx":{"chunks":[0,1,13,2,6],"assets":["styles.b6947980c7644db60460.css","styles-be8105c56c1a09dbbca6.js","styles-be8105c56c1a09dbbca6.js.map","1-2d947e67ed2878270b86.js","1-2d947e67ed2878270b86.js.map","13-628c2720cacfa3e7d297.js","13-628c2720cacfa3e7d297.js.map","2-ee542a1a022b7a037d70.js","2-ee542a1a022b7a037d70.js.map","component---src-pages-index-jsx-15b61ae27c858896f32e.js","component---src-pages-index-jsx-15b61ae27c858896f32e.js.map"],"children":{},"childAssets":{}},"component---src-pages-team-jsx":{"chunks":[0,1,2,7],"assets":["styles.b6947980c7644db60460.css","styles-be8105c56c1a09dbbca6.js","styles-be8105c56c1a09dbbca6.js.map","1-2d947e67ed2878270b86.js","1-2d947e67ed2878270b86.js.map","2-ee542a1a022b7a037d70.js","2-ee542a1a022b7a037d70.js.map","component---src-pages-team-jsx-87f89941bc7509c1fb0e.js","component---src-pages-team-jsx-87f89941bc7509c1fb0e.js.map"],"children":{},"childAssets":{}},"pages-manifest":{"chunks":[10],"assets":["pages-manifest-84617a459d3ce657d51a.js","pages-manifest-84617a459d3ce657d51a.js.map"],"children":{},"childAssets":{}}},"assetsByChunkName":{"app":["webpack-runtime-3320b42780cefc6625f2.js","styles.b6947980c7644db60460.css","styles-be8105c56c1a09dbbca6.js","app-a7fe1f09c92da344b0fd.js"],"component---src-templates-case-study-jsx":["styles.b6947980c7644db60460.css","styles-be8105c56c1a09dbbca6.js","1-2d947e67ed2878270b86.js","2-ee542a1a022b7a037d70.js","component---src-templates-case-study-jsx-dedb2418065911020a35.js"],"component---src-templates-blog-jsx":["styles.b6947980c7644db60460.css","styles-be8105c56c1a09dbbca6.js","1-2d947e67ed2878270b86.js","12-e8ccbfaec0dc63ed60c8.js","2-ee542a1a022b7a037d70.js","component---src-templates-blog-jsx-bde74e2a60b696371382.js"],"component---src-pages-404-jsx":["styles.b6947980c7644db60460.css","styles-be8105c56c1a09dbbca6.js","1-2d947e67ed2878270b86.js","2-ee542a1a022b7a037d70.js","component---src-pages-404-jsx-b407729bf74e3ba0101e.js"],"component---src-pages-blog-jsx":["styles.b6947980c7644db60460.css","styles-be8105c56c1a09dbbca6.js","1-2d947e67ed2878270b86.js","2-ee542a1a022b7a037d70.js","component---src-pages-blog-jsx-b59c7f80df31187fe70d.js"],"component---src-pages-index-jsx":["styles.b6947980c7644db60460.css","styles-be8105c56c1a09dbbca6.js","1-2d947e67ed2878270b86.js","13-628c2720cacfa3e7d297.js","2-ee542a1a022b7a037d70.js","component---src-pages-index-jsx-15b61ae27c858896f32e.js"],"component---src-pages-team-jsx":["styles.b6947980c7644db60460.css","styles-be8105c56c1a09dbbca6.js","1-2d947e67ed2878270b86.js","2-ee542a1a022b7a037d70.js","component---src-pages-team-jsx-87f89941bc7509c1fb0e.js"],"pages-manifest":["pages-manifest-84617a459d3ce657d51a.js"]}}